robloxrequestsss/__init__.py
robloxrequestsss/robloxrequests.py
robloxrequestsss-0.1.dist-info/METADATA
robloxrequestsss-0.1.dist-info/WHEEL
robloxrequestsss-0.1.dist-info/top_level.txt
robloxrequestsss-0.1.dist-info/RECORD
