Metadata-Version: 2.1
Name: robloxrequestsss
Version: 0.1
Summary: robloxrequestsss
